deepspellchecker/__init__.py
deepspellchecker-0.0.1.dist-info/LICENSE
deepspellchecker-0.0.1.dist-info/METADATA
deepspellchecker-0.0.1.dist-info/WHEEL
deepspellchecker-0.0.1.dist-info/top_level.txt
deepspellchecker-0.0.1.dist-info/RECORD
